[{"host":{"consumption":3115192.0,"timestamp":1681683554.4920425},"consumers":[{"exe":"","pid":952,"consumption":0.0,"timestamp":1681683554.5011382,"container":null},{"exe":"C:\\Windows\\System32\\svchost.exe","pid":18796,"consumption":0.0,"timestamp":1681683554.5011444,"container":null},{"exe":"","pid":10504,"consumption":0.0,"timestamp":1681683554.5011463,"container":null},{"exe":"","pid":1752,"consumption":0.0,"timestamp":1681683554.5011477,"container":null},{"exe":"C:\\Windows\\System32\\svchost.exe","pid":15992,"consumption":0.0,"timestamp":1681683554.5011492,"container":null},{"exe":"","pid":4720,"consumption":0.0,"timestamp":1681683554.5011506,"container":null},{"exe":"","pid":4488,"consumption":0.0,"timestamp":1681683554.5011525,"container":null},{"exe":"","pid":1392,"consumption":0.0,"timestamp":1681683554.5011542,"container":null},{"exe":"","pid":2000,"consumption":0.0,"timestamp":1681683554.501156,"container":null},{"exe":"C:\\Windows\\SystemApps\\Microsoft.LockApp_cw5n1h2txyewy\\LockApp.exe","pid":21600,"consumption":0.0,"timestamp":1681683554.5011578,"container":null},{"exe":"","pid":4596,"consumption":0.0,"timestamp":1681683554.5011601,"container":null},{"exe":"","pid":9140,"consumption":0.0,"timestamp":1681683554.5011623,"container":null},{"exe":"","pid":2640,"consumption":0.0,"timestamp":1681683554.5011642,"container":null},{"exe":"C:\\Program Files\\Realtek\\Audio\\HDA\\RtkNGUI64.exe","pid":17548,"consumption":0.0,"timestamp":1681683554.501166,"container":null},{"exe":"C:\\Windows\\py.exe","pid":20708,"consumption":0.0,"timestamp":1681683554.501168,"container":null},{"exe":"","pid":21188,"consumption":0.0,"timestamp":1681683554.5011702,"container":null},{"exe":"","pid":12356,"consumption":0.0,"timestamp":1681683554.501172,"container":null},{"exe":"C:\\Program Files\\WindowsApps\\MicrosoftWindows.Client.WebExperience_423.8900.0.0_x64__cw5n1h2txyewy\\Dashboard\\Widgets.exe","pid":18132,"consumption":0.0,"timestamp":1681683554.501174,"container":null},{"exe":"","pid":4352,"consumption":0.0,"timestamp":1681683554.501176,"container":null},{"exe":"","pid":5388,"consumption":0.0,"timestamp":1681683554.501178,"container":null},{"exe":"","pid":1252,"consumption":0.0,"timestamp":1681683554.5011802,"container":null},{"exe":"","pid":22208,"consumption":0.0,"timestamp":1681683554.5011823,"container":null},{"exe":"C:\\Windows\\System32\\RuntimeBroker.exe","pid":6204,"consumption":0.0,"timestamp":1681683554.5011842,"container":null},{"exe":"","pid":2976,"consumption":0.0,"timestamp":1681683554.5011866,"container":null},{"exe":"","pid":3276,"consumption":0.0,"timestamp":1681683554.5011892,"container":null},{"exe":"","pid":6816,"consumption":0.0,"timestamp":1681683554.5011916,"container":null},{"exe":"","pid":1988,"consumption":0.0,"timestamp":1681683554.501194,"container":null},{"exe":"","pid":14284,"consumption":0.0,"timestamp":1681683554.5011964,"container":null},{"exe":"","pid":7708,"consumption":0.0,"timestamp":1681683554.501199,"container":null},{"exe":"","pid":2868,"consumption":0.0,"timestamp":1681683554.5012019,"container":null},{"exe":"C:\\Windows\\System32\\dllhost.exe","pid":16420,"consumption":0.0,"timestamp":1681683554.5012045,"container":null},{"exe":"","pid":9800,"consumption":0.0,"timestamp":1681683554.5012074,"container":null},{"exe":"","pid":1932,"consumption":0.0,"timestamp":1681683554.50121,"container":null},{"exe":"","pid":3360,"consumption":0.0,"timestamp":1681683554.501213,"container":null},{"exe":"C:\\Program Files\\WindowsApps\\ReaderNotificationClient_1.0.4.0_x86__e1rzdqpraam7r\\AcrobatNotificationClient.exe","pid":15528,"consumption":0.0,"timestamp":1681683554.5012162,"container":null},{"exe":"","pid":4124,"consumption":0.0,"timestamp":1681683554.5012193,"container":null},{"exe":"","pid":3196,"consumption":0.0,"timestamp":1681683554.5012407,"container":null},{"exe":"C:\\Windows\\System32\\SecurityHealthSystray.exe","pid":20132,"consumption":0.0,"timestamp":1681683554.5012436,"container":null},{"exe":"","pid":4548,"consumption":0.0,"timestamp":1681683554.501247,"container":null},{"exe":"","pid":5840,"consumption":0.0,"timestamp":1681683554.5012503,"container":null},{"exe":"C:\\Program Files\\Waves\\MaxxAudio\\WavesSvc64.exe","pid":15916,"consumption":0.0,"timestamp":1681683554.5012536,"container":null},{"exe":"","pid":14128,"consumption":0.0,"timestamp":1681683554.5012572,"container":null},{"exe":"C:\\Windows\\System32\\backgroundTaskHost.exe","pid":14444,"consumption":0.0,"timestamp":1681683554.5012605,"container":null},{"exe":"","pid":11072,"consumption":0.0,"timestamp":1681683554.501264,"container":null},{"exe":"","pid":2616,"consumption":0.0,"timestamp":1681683554.5012674,"container":null},{"exe":"","pid":3248,"consumption":0.0,"timestamp":1681683554.5012708,"container":null},{"exe":"C:\\Windows\\SystemApps\\MicrosoftWindows.Client.CBS_cw5n1h2txyewy\\TextInputHost.exe","pid":9148,"consumption":0.0,"timestamp":1681683554.501274,"container":null},{"exe":"","pid":4236,"consumption":0.0,"timestamp":1681683554.5012777,"container":null},{"exe":"","pid":4480,"consumption":0.0,"timestamp":1681683554.5012815,"container":null},{"exe":"","pid":8516,"consumption":0.0,"timestamp":1681683554.501285,"container":null},{"exe":"C:\\Windows\\SystemApps\\MicrosoftWindows.Client.CBS_cw5n1h2txyewy\\SearchHost.exe","pid":8336,"consumption":0.0,"timestamp":1681683554.5012887,"container":null},{"exe":"","pid":3780,"consumption":0.0,"timestamp":1681683554.5012925,"container":null},{"exe":"","pid":5776,"consumption":0.0,"timestamp":1681683554.501304,"container":null},{"exe":"","pid":0,"consumption":0.0,"timestamp":1681683554.501308,"container":null},{"exe":"","pid":2664,"consumption":0.0,"timestamp":1681683554.5013258,"container":null},{"exe":"","pid":11760,"consumption":0.0,"timestamp":1681683554.5013301,"container":null},{"exe":"C:\\Program Files\\erl-23.3.4.11\\bin\\erl.exe","pid":4372,"consumption":0.0,"timestamp":1681683554.5013342,"container":null},{"exe":"","pid":4036,"consumption":0.0,"timestamp":1681683554.5013394,"container":null},{"exe":"C:\\Program Files\\Common Files\\microsoft shared\\ClickToRun\\AppVShNotify.exe","pid":10508,"consumption":0.0,"timestamp":1681683554.501344,"container":null},{"exe":"","pid":2784,"consumption":0.0,"timestamp":1681683554.5013485,"container":null},{"exe":"","pid":4300,"consumption":0.0,"timestamp":1681683554.501353,"container":null},{"exe":"","pid":2912,"consumption":0.0,"timestamp":1681683554.5013776,"container":null},{"exe":"","pid":3432,"consumption":0.0,"timestamp":1681683554.5013826,"container":null},{"exe":"","pid":796,"consumption":0.0,"timestamp":1681683554.5013871,"container":null},{"exe":"C:\\Windows\\System32\\backgroundTaskHost.exe","pid":12932,"consumption":0.0,"timestamp":1681683554.5013916,"container":null},{"exe":"","pid":2608,"consumption":0.0,"timestamp":1681683554.5013964,"container":null},{"exe":"","pid":4508,"consumption":0.0,"timestamp":1681683554.5014012,"container":null},{"exe":"","pid":9288,"consumption":0.0,"timestamp":1681683554.501406,"container":null},{"exe":"","pid":7108,"consumption":0.0,"timestamp":1681683554.5014105,"container":null},{"exe":"","pid":4448,"consumption":0.0,"timestamp":1681683554.5014153,"container":null},{"exe":"C:\\Windows\\System32\\svchost.exe","pid":20592,"consumption":0.0,"timestamp":1681683554.50142,"container":null},{"exe":"C:\\Program Files (x86)\\Microsoft\\Edge\\Application\\msedge.exe","pid":21856,"consumption":0.0,"timestamp":1681683554.501425,"container":null},{"exe":"","pid":4500,"consumption":0.0,"timestamp":1681683554.50143,"container":null},{"exe":"","pid":2268,"consumption":0.0,"timestamp":1681683554.5014355,"container":null},{"exe":"","pid":3564,"consumption":0.0,"timestamp":1681683554.5014405,"container":null},{"exe":"C:\\Windows\\System32\\RuntimeBroker.exe","pid":17948,"consumption":0.0,"timestamp":1681683554.5014458,"container":null},{"exe":"","pid":5376,"consumption":0.0,"timestamp":1681683554.501451,"container":null},{"exe":"","pid":2152,"consumption":0.0,"timestamp":1681683554.501456,"container":null},{"exe":"C:\\Windows\\System32\\svchost.exe","pid":11060,"consumption":0.0,"timestamp":1681683554.5014613,"container":null},{"exe":"","pid":13964,"consumption":0.0,"timestamp":1681683554.5014665,"container":null},{"exe":"","pid":4144,"consumption":0.0,"timestamp":1681683554.501472,"container":null},{"exe":"","pid":5544,"consumption":0.0,"timestamp":1681683554.5014777,"container":null},{"exe":"","pid":624,"consumption":0.0,"timestamp":1681683554.5014837,"container":null},{"exe":"C:\\Windows\\System32\\backgroundTaskHost.exe","pid":17396,"consumption":0.0,"timestamp":1681683554.5014894,"container":null},{"exe":"C:\\Program Files\\Realtek\\Audio\\HDA\\RAVBg64.exe","pid":16284,"consumption":0.0,"timestamp":1681683554.501495,"container":null},{"exe":"","pid":2056,"consumption":0.0,"timestamp":1681683554.5015006,"container":null},{"exe":"C:\\Program Files (x86)\\Microsoft\\Edge\\Application\\msedge.exe","pid":6764,"consumption":0.0,"timestamp":1681683554.5015256,"container":null},{"exe":"C:\\Windows\\System32\\svchost.exe","pid":12312,"consumption":0.0,"timestamp":1681683554.5015316,"container":null},{"exe":"C:\\Windows\\System32\\taskhostw.exe","pid":12892,"consumption":0.0,"timestamp":1681683554.5015376,"container":null},{"exe":"C:\\Windows\\System32\\svchost.exe","pid":5256,"consumption":0.0,"timestamp":1681683554.5015435,"container":null},{"exe":"C:\\Windows\\explorer.exe","pid":8736,"consumption":0.0,"timestamp":1681683554.5015495,"container":null},{"exe":"","pid":3840,"consumption":0.0,"timestamp":1681683554.5015557,"container":null},{"exe":"C:\\Windows\\System32\\RuntimeBroker.exe","pid":9892,"consumption":0.0,"timestamp":1681683554.5015619,"container":null},{"exe":"C:\\Program Files\\Dell\\Dell Peripheral Manager\\DPM.exe","pid":11720,"consumption":0.0,"timestamp":1681683554.501568,"container":null},{"exe":"","pid":4704,"consumption":0.0,"timestamp":1681683554.5015762,"container":null},{"exe":"","pid":3336,"consumption":0.0,"timestamp":1681683554.5015824,"container":null},{"exe":"C:\\Windows\\System32\\RuntimeBroker.exe","pid":18940,"consumption":0.0,"timestamp":1681683554.5015888,"container":null},{"exe":"","pid":1636,"consumption":0.0,"timestamp":1681683554.5015955,"container":null},{"exe":"","pid":1308,"consumption":0.0,"timestamp":1681683554.5016017,"container":null},{"exe":"","pid":2480,"consumption":0.0,"timestamp":1681683554.5016081,"container":null}],"sockets":[]}]