[{"host":{"consumption":8792513.0,"timestamp":1681744780.4764223},"consumers":[{"exe":"C:\\Program Files\\erl-23.3.4.11\\bin\\erl.exe","pid":9460,"consumption":1036617.44,"timestamp":1681744780.4822216,"container":null},{"exe":"C:\\Windows\\explorer.exe","pid":16684,"consumption":0.0,"timestamp":1681744780.4821508,"container":null},{"exe":"C:\\Windows\\System32\\backgroundTaskHost.exe","pid":19848,"consumption":0.0,"timestamp":1681744780.4821575,"container":null},{"exe":"C:\\Windows\\System32\\ApplicationFrameHost.exe","pid":18076,"consumption":0.0,"timestamp":1681744780.4821596,"container":null},{"exe":"","pid":4772,"consumption":0.0,"timestamp":1681744780.4821613,"container":null},{"exe":"","pid":9140,"consumption":0.0,"timestamp":1681744780.482163,"container":null},{"exe":"","pid":3564,"consumption":0.0,"timestamp":1681744780.4821646,"container":null},{"exe":"","pid":13904,"consumption":0.0,"timestamp":1681744780.4821663,"container":null},{"exe":"","pid":1504,"consumption":0.0,"timestamp":1681744780.482168,"container":null},{"exe":"C:\\Windows\\System32\\Intel\\DPTF\\dptf_helper.exe","pid":12468,"consumption":0.0,"timestamp":1681744780.4821694,"container":null},{"exe":"","pid":12356,"consumption":0.0,"timestamp":1681744780.4821732,"container":null},{"exe":"","pid":1820,"consumption":0.0,"timestamp":1681744780.4821756,"container":null},{"exe":"","pid":4508,"consumption":0.0,"timestamp":1681744780.482177,"container":null},{"exe":"","pid":3432,"consumption":0.0,"timestamp":1681744780.4821787,"container":null},{"exe":"","pid":2152,"consumption":0.0,"timestamp":1681744780.4821806,"container":null},{"exe":"","pid":9224,"consumption":0.0,"timestamp":1681744780.4821823,"container":null},{"exe":"","pid":776,"consumption":0.0,"timestamp":1681744780.4821842,"container":null},{"exe":"C:\\Program Files\\WindowsApps\\ReaderNotificationClient_1.0.4.0_x86__e1rzdqpraam7r\\AcrobatNotificationClient.exe","pid":15372,"consumption":0.0,"timestamp":1681744780.482187,"container":null},{"exe":"","pid":2976,"consumption":0.0,"timestamp":1681744780.4821892,"container":null},{"exe":"C:\\scaphandre\\target\\debug\\scaphandre.exe","pid":17220,"consumption":0.0,"timestamp":1681744780.482191,"container":null},{"exe":"","pid":1896,"consumption":0.0,"timestamp":1681744780.482193,"container":null},{"exe":"","pid":708,"consumption":0.0,"timestamp":1681744780.4821951,"container":null},{"exe":"","pid":3780,"consumption":0.0,"timestamp":1681744780.482197,"container":null},{"exe":"C:\\Windows\\System32\\RuntimeBroker.exe","pid":3236,"consumption":0.0,"timestamp":1681744780.4822102,"container":null},{"exe":"C:\\Program Files\\WindowsApps\\Microsoft.YourPhone_1.23022.140.0_x64__8wekyb3d8bbwe\\PhoneExperienceHost.exe","pid":17080,"consumption":0.0,"timestamp":1681744780.4822125,"container":null},{"exe":"","pid":6816,"consumption":0.0,"timestamp":1681744780.4822147,"container":null},{"exe":"","pid":1760,"consumption":0.0,"timestamp":1681744780.4822168,"container":null},{"exe":"C:\\Windows\\SystemApps\\Microsoft.LockApp_cw5n1h2txyewy\\LockApp.exe","pid":2980,"consumption":0.0,"timestamp":1681744780.4822192,"container":null},{"exe":"","pid":3000,"consumption":0.0,"timestamp":1681744780.482224,"container":null},{"exe":"","pid":15816,"consumption":0.0,"timestamp":1681744780.4822276,"container":null},{"exe":"","pid":8516,"consumption":0.0,"timestamp":1681744780.4822302,"container":null},{"exe":"C:\\Windows\\System32\\svchost.exe","pid":15660,"consumption":0.0,"timestamp":1681744780.4822335,"container":null},{"exe":"","pid":1092,"consumption":0.0,"timestamp":1681744780.4822366,"container":null},{"exe":"","pid":2436,"consumption":0.0,"timestamp":1681744780.4822397,"container":null},{"exe":"","pid":3536,"consumption":0.0,"timestamp":1681744780.4822464,"container":null},{"exe":"C:\\Windows\\System32\\svchost.exe","pid":20928,"consumption":0.0,"timestamp":1681744780.4822495,"container":null},{"exe":"","pid":3720,"consumption":0.0,"timestamp":1681744780.4822526,"container":null},{"exe":"","pid":4564,"consumption":0.0,"timestamp":1681744780.4822555,"container":null},{"exe":"","pid":11780,"consumption":0.0,"timestamp":1681744780.4822583,"container":null},{"exe":"C:\\Windows\\System32\\svchost.exe","pid":18060,"consumption":0.0,"timestamp":1681744780.4822738,"container":null},{"exe":"","pid":3336,"consumption":0.0,"timestamp":1681744780.4822981,"container":null},{"exe":"","pid":8756,"consumption":0.0,"timestamp":1681744780.4823024,"container":null},{"exe":"","pid":108,"consumption":0.0,"timestamp":1681744780.4823065,"container":null},{"exe":"","pid":4464,"consumption":0.0,"timestamp":1681744780.4823103,"container":null},{"exe":"C:\\Windows\\System32\\DriverStore\\FileRepository\\cui_dch.inf_amd64_7208949846a9b9dc\\igfxEM.exe","pid":10304,"consumption":0.0,"timestamp":1681744780.482315,"container":null},{"exe":"","pid":2000,"consumption":0.0,"timestamp":1681744780.482319,"container":null},{"exe":"","pid":2912,"consumption":0.0,"timestamp":1681744780.4823244,"container":null},{"exe":"C:\\Windows\\System32\\svchost.exe","pid":10180,"consumption":0.0,"timestamp":1681744780.482329,"container":null},{"exe":"","pid":4588,"consumption":0.0,"timestamp":1681744780.4823337,"container":null},{"exe":"","pid":11528,"consumption":0.0,"timestamp":1681744780.4823384,"container":null},{"exe":"","pid":3756,"consumption":0.0,"timestamp":1681744780.4823432,"container":null},{"exe":"","pid":4004,"consumption":0.0,"timestamp":1681744780.4823484,"container":null},{"exe":"C:\\Windows\\SystemApps\\MicrosoftWindows.Client.CBS_cw5n1h2txyewy\\TextInputHost.exe","pid":21300,"consumption":0.0,"timestamp":1681744780.4823685,"container":null},{"exe":"","pid":11072,"consumption":0.0,"timestamp":1681744780.482373,"container":null},{"exe":"","pid":1988,"consumption":0.0,"timestamp":1681744780.482378,"container":null},{"exe":"","pid":3276,"consumption":0.0,"timestamp":1681744780.4823828,"container":null},{"exe":"","pid":9800,"consumption":0.0,"timestamp":1681744780.4823873,"container":null},{"exe":"","pid":17588,"consumption":0.0,"timestamp":1681744780.482392,"container":null},{"exe":"","pid":11328,"consumption":0.0,"timestamp":1681744780.4823983,"container":null},{"exe":"C:\\Windows\\System32\\oobe\\UserOOBEBroker.exe","pid":5772,"consumption":0.0,"timestamp":1681744780.4824035,"container":null},{"exe":"","pid":1184,"consumption":0.0,"timestamp":1681744780.4824092,"container":null},{"exe":"C:\\Program Files\\WindowsApps\\MicrosoftWindows.Client.WebExperience_423.8900.0.0_x64__cw5n1h2txyewy\\Dashboard\\Widgets.exe","pid":13968,"consumption":0.0,"timestamp":1681744780.482414,"container":null},{"exe":"","pid":952,"consumption":0.0,"timestamp":1681744780.482423,"container":null},{"exe":"","pid":1904,"consumption":0.0,"timestamp":1681744780.4824288,"container":null},{"exe":"","pid":4704,"consumption":0.0,"timestamp":1681744780.482438,"container":null},{"exe":"","pid":5376,"consumption":0.0,"timestamp":1681744780.4824443,"container":null},{"exe":"C:\\Windows\\System32\\RuntimeBroker.exe","pid":11388,"consumption":0.0,"timestamp":1681744780.4824502,"container":null},{"exe":"","pid":6176,"consumption":0.0,"timestamp":1681744780.4824564,"container":null},{"exe":"","pid":4448,"consumption":0.0,"timestamp":1681744780.4824612,"container":null},{"exe":"","pid":2608,"consumption":0.0,"timestamp":1681744780.482466,"container":null},{"exe":"","pid":4480,"consumption":0.0,"timestamp":1681744780.482483,"container":null},{"exe":"","pid":3360,"consumption":0.0,"timestamp":1681744780.482488,"container":null},{"exe":"C:\\Windows\\py.exe","pid":16520,"consumption":0.0,"timestamp":1681744780.4824927,"container":null},{"exe":"","pid":4616,"consumption":0.0,"timestamp":1681744780.482499,"container":null},{"exe":"","pid":2744,"consumption":0.0,"timestamp":1681744780.4825037,"container":null},{"exe":"C:\\Program Files\\Realtek\\Audio\\HDA\\RAVBg64.exe","pid":4248,"consumption":0.0,"timestamp":1681744780.4825087,"container":null},{"exe":"","pid":1308,"consumption":0.0,"timestamp":1681744780.482514,"container":null},{"exe":"C:\\Windows\\System32\\conhost.exe","pid":6264,"consumption":0.0,"timestamp":1681744780.482519,"container":null},{"exe":"","pid":3132,"consumption":0.0,"timestamp":1681744780.482524,"container":null},{"exe":"C:\\Windows\\System32\\RuntimeBroker.exe","pid":13160,"consumption":0.0,"timestamp":1681744780.482531,"container":null},{"exe":"C:\\Windows\\System32\\RuntimeBroker.exe","pid":21816,"consumption":0.0,"timestamp":1681744780.4825373,"container":null},{"exe":"","pid":4136,"consumption":0.0,"timestamp":1681744780.4825428,"container":null},{"exe":"","pid":10084,"consumption":0.0,"timestamp":1681744780.482553,"container":null},{"exe":"C:\\Windows\\System32\\SecurityHealthSystray.exe","pid":16284,"consumption":0.0,"timestamp":1681744780.4825585,"container":null},{"exe":"C:\\Windows\\ImmersiveControlPanel\\SystemSettings.exe","pid":6792,"consumption":0.0,"timestamp":1681744780.4825644,"container":null},{"exe":"","pid":5388,"consumption":0.0,"timestamp":1681744780.4825702,"container":null},{"exe":"C:\\Windows\\SystemApps\\Microsoft.Windows.StartMenuExperienceHost_cw5n1h2txyewy\\StartMenuExperienceHost.exe","pid":17452,"consumption":0.0,"timestamp":1681744780.482576,"container":null},{"exe":"","pid":3196,"consumption":0.0,"timestamp":1681744780.4825816,"container":null},{"exe":"C:\\Windows\\System32\\dllhost.exe","pid":5972,"consumption":0.0,"timestamp":1681744780.4826038,"container":null},{"exe":"","pid":148,"consumption":0.0,"timestamp":1681744780.4826095,"container":null},{"exe":"C:\\Windows\\System32\\svchost.exe","pid":12088,"consumption":0.0,"timestamp":1681744780.4826152,"container":null},{"exe":"","pid":5520,"consumption":0.0,"timestamp":1681744780.482621,"container":null},{"exe":"C:\\Windows\\System32\\RuntimeBroker.exe","pid":12540,"consumption":0.0,"timestamp":1681744780.4826267,"container":null},{"exe":"","pid":2640,"consumption":0.0,"timestamp":1681744780.4826329,"container":null},{"exe":"","pid":6412,"consumption":0.0,"timestamp":1681744780.4826386,"container":null},{"exe":"","pid":3172,"consumption":0.0,"timestamp":1681744780.4826446,"container":null},{"exe":"","pid":7864,"consumption":0.0,"timestamp":1681744780.4826505,"container":null},{"exe":"C:\\Windows\\SystemApps\\MicrosoftWindows.Client.CBS_cw5n1h2txyewy\\SearchHost.exe","pid":17620,"consumption":0.0,"timestamp":1681744780.4826565,"container":null},{"exe":"","pid":1428,"consumption":0.0,"timestamp":1681744780.4826624,"container":null},{"exe":"","pid":7812,"consumption":0.0,"timestamp":1681744780.4826753,"container":null}],"sockets":[]},{"host":{"consumption":11806361.0,"timestamp":1681744781.5077019},"consumers":[{"exe":"C:\\Program Files\\erl-23.3.4.11\\bin\\erl.exe","pid":9460,"consumption":2006121.1,"timestamp":1681744781.5130794,"container":null},{"exe":"C:\\Windows\\explorer.exe","pid":16684,"consumption":0.0,"timestamp":1681744781.5130346,"container":null},{"exe":"C:\\Windows\\System32\\backgroundTaskHost.exe","pid":19848,"consumption":0.0,"timestamp":1681744781.513038,"container":null},{"exe":"C:\\Windows\\System32\\ApplicationFrameHost.exe","pid":18076,"consumption":0.0,"timestamp":1681744781.513039,"container":null},{"exe":"","pid":4772,"consumption":0.0,"timestamp":1681744781.5130403,"container":null},{"exe":"","pid":9140,"consumption":0.0,"timestamp":1681744781.5130415,"container":null},{"exe":"","pid":3564,"consumption":0.0,"timestamp":1681744781.5130427,"container":null},{"exe":"","pid":13904,"consumption":0.0,"timestamp":1681744781.5130439,"container":null},{"exe":"","pid":1504,"consumption":0.0,"timestamp":1681744781.5130448,"container":null},{"exe":"C:\\Windows\\System32\\Intel\\DPTF\\dptf_helper.exe","pid":12468,"consumption":0.0,"timestamp":1681744781.513046,"container":null},{"exe":"","pid":12356,"consumption":0.0,"timestamp":1681744781.5130475,"container":null},{"exe":"","pid":1820,"consumption":0.0,"timestamp":1681744781.513049,"container":null},{"exe":"","pid":4508,"consumption":0.0,"timestamp":1681744781.51305,"container":null},{"exe":"","pid":3432,"consumption":0.0,"timestamp":1681744781.5130513,"container":null},{"exe":"","pid":2152,"consumption":0.0,"timestamp":1681744781.5130532,"container":null},{"exe":"","pid":9224,"consumption":0.0,"timestamp":1681744781.5130546,"container":null},{"exe":"","pid":776,"consumption":0.0,"timestamp":1681744781.5130563,"container":null},{"exe":"C:\\Program Files\\WindowsApps\\ReaderNotificationClient_1.0.4.0_x86__e1rzdqpraam7r\\AcrobatNotificationClient.exe","pid":15372,"consumption":0.0,"timestamp":1681744781.5130577,"container":null},{"exe":"","pid":2976,"consumption":0.0,"timestamp":1681744781.5130594,"container":null},{"exe":"C:\\scaphandre\\target\\debug\\scaphandre.exe","pid":17220,"consumption":0.0,"timestamp":1681744781.513061,"container":null},{"exe":"","pid":1896,"consumption":0.0,"timestamp":1681744781.5130627,"container":null},{"exe":"","pid":708,"consumption":0.0,"timestamp":1681744781.5130646,"container":null},{"exe":"","pid":3780,"consumption":0.0,"timestamp":1681744781.5130665,"container":null},{"exe":"C:\\Windows\\System32\\RuntimeBroker.exe","pid":3236,"consumption":0.0,"timestamp":1681744781.5130687,"container":null},{"exe":"C:\\Program Files\\WindowsApps\\Microsoft.YourPhone_1.23022.140.0_x64__8wekyb3d8bbwe\\PhoneExperienceHost.exe","pid":17080,"consumption":0.0,"timestamp":1681744781.5130708,"container":null},{"exe":"","pid":6816,"consumption":0.0,"timestamp":1681744781.5130732,"container":null},{"exe":"","pid":1760,"consumption":0.0,"timestamp":1681744781.513075,"container":null},{"exe":"C:\\Windows\\SystemApps\\Microsoft.LockApp_cw5n1h2txyewy\\LockApp.exe","pid":2980,"consumption":0.0,"timestamp":1681744781.5130773,"container":null},{"exe":"","pid":3000,"consumption":0.0,"timestamp":1681744781.5130816,"container":null},{"exe":"","pid":15816,"consumption":0.0,"timestamp":1681744781.513084,"container":null},{"exe":"","pid":8516,"consumption":0.0,"timestamp":1681744781.5130863,"container":null},{"exe":"C:\\Windows\\System32\\svchost.exe","pid":15660,"consumption":0.0,"timestamp":1681744781.5130885,"container":null},{"exe":"","pid":1092,"consumption":0.0,"timestamp":1681744781.5130908,"container":null},{"exe":"","pid":2436,"consumption":0.0,"timestamp":1681744781.5130935,"container":null},{"exe":"","pid":3536,"consumption":0.0,"timestamp":1681744781.513096,"container":null},{"exe":"C:\\Windows\\System32\\svchost.exe","pid":20928,"consumption":0.0,"timestamp":1681744781.5130987,"container":null},{"exe":"","pid":3720,"consumption":0.0,"timestamp":1681744781.5131016,"container":null},{"exe":"","pid":4564,"consumption":0.0,"timestamp":1681744781.5131042,"container":null},{"exe":"","pid":11780,"consumption":0.0,"timestamp":1681744781.513107,"container":null},{"exe":"C:\\Windows\\System32\\svchost.exe","pid":18060,"consumption":0.0,"timestamp":1681744781.51311,"container":null},{"exe":"","pid":3336,"consumption":0.0,"timestamp":1681744781.513113,"container":null},{"exe":"","pid":8756,"consumption":0.0,"timestamp":1681744781.513116,"container":null},{"exe":"","pid":108,"consumption":0.0,"timestamp":1681744781.513119,"container":null},{"exe":"","pid":4464,"consumption":0.0,"timestamp":1681744781.513122,"container":null},{"exe":"C:\\Windows\\System32\\DriverStore\\FileRepository\\cui_dch.inf_amd64_7208949846a9b9dc\\igfxEM.exe","pid":10304,"consumption":0.0,"timestamp":1681744781.5131252,"container":null},{"exe":"","pid":2000,"consumption":0.0,"timestamp":1681744781.5131285,"container":null},{"exe":"","pid":2912,"consumption":0.0,"timestamp":1681744781.5131316,"container":null},{"exe":"C:\\Windows\\System32\\svchost.exe","pid":10180,"consumption":0.0,"timestamp":1681744781.5131347,"container":null},{"exe":"","pid":4588,"consumption":0.0,"timestamp":1681744781.513138,"container":null},{"exe":"","pid":11528,"consumption":0.0,"timestamp":1681744781.5131414,"container":null},{"exe":"","pid":3756,"consumption":0.0,"timestamp":1681744781.5131447,"container":null},{"exe":"","pid":4004,"consumption":0.0,"timestamp":1681744781.513148,"container":null},{"exe":"C:\\Windows\\SystemApps\\MicrosoftWindows.Client.CBS_cw5n1h2txyewy\\TextInputHost.exe","pid":21300,"consumption":0.0,"timestamp":1681744781.5131516,"container":null},{"exe":"","pid":11072,"consumption":0.0,"timestamp":1681744781.5131552,"container":null},{"exe":"","pid":1988,"consumption":0.0,"timestamp":1681744781.5131588,"container":null},{"exe":"","pid":3276,"consumption":0.0,"timestamp":1681744781.5131624,"container":null},{"exe":"","pid":9800,"consumption":0.0,"timestamp":1681744781.5131664,"container":null},{"exe":"","pid":17588,"consumption":0.0,"timestamp":1681744781.51317,"container":null},{"exe":"","pid":11328,"consumption":0.0,"timestamp":1681744781.5131738,"container":null},{"exe":"C:\\Windows\\System32\\oobe\\UserOOBEBroker.exe","pid":5772,"consumption":0.0,"timestamp":1681744781.5131776,"container":null},{"exe":"","pid":1184,"consumption":0.0,"timestamp":1681744781.5131817,"container":null},{"exe":"C:\\Program Files\\WindowsApps\\MicrosoftWindows.Client.WebExperience_423.8900.0.0_x64__cw5n1h2txyewy\\Dashboard\\Widgets.exe","pid":13968,"consumption":0.0,"timestamp":1681744781.5131853,"container":null},{"exe":"","pid":952,"consumption":0.0,"timestamp":1681744781.5131893,"container":null},{"exe":"","pid":1904,"consumption":0.0,"timestamp":1681744781.5131934,"container":null},{"exe":"","pid":4704,"consumption":0.0,"timestamp":1681744781.5131977,"container":null},{"exe":"","pid":5376,"consumption":0.0,"timestamp":1681744781.5132017,"container":null},{"exe":"C:\\Windows\\System32\\RuntimeBroker.exe","pid":11388,"consumption":0.0,"timestamp":1681744781.513206,"container":null},{"exe":"","pid":6176,"consumption":0.0,"timestamp":1681744781.5132103,"container":null},{"exe":"","pid":4448,"consumption":0.0,"timestamp":1681744781.5132148,"container":null},{"exe":"","pid":2608,"consumption":0.0,"timestamp":1681744781.5132196,"container":null},{"exe":"","pid":4480,"consumption":0.0,"timestamp":1681744781.513224,"container":null},{"exe":"","pid":3360,"consumption":0.0,"timestamp":1681744781.5132291,"container":null},{"exe":"C:\\Windows\\py.exe","pid":16520,"consumption":0.0,"timestamp":1681744781.5132337,"container":null},{"exe":"","pid":4616,"consumption":0.0,"timestamp":1681744781.5132384,"container":null},{"exe":"","pid":2744,"consumption":0.0,"timestamp":1681744781.5132432,"container":null},{"exe":"C:\\Program Files\\Realtek\\Audio\\HDA\\RAVBg64.exe","pid":4248,"consumption":0.0,"timestamp":1681744781.5132475,"container":null},{"exe":"","pid":1308,"consumption":0.0,"timestamp":1681744781.5132525,"container":null},{"exe":"C:\\Windows\\System32\\conhost.exe","pid":6264,"consumption":0.0,"timestamp":1681744781.513257,"container":null},{"exe":"","pid":3132,"consumption":0.0,"timestamp":1681744781.5132618,"container":null},{"exe":"C:\\Windows\\System32\\RuntimeBroker.exe","pid":13160,"consumption":0.0,"timestamp":1681744781.5132668,"container":null},{"exe":"C:\\Windows\\System32\\RuntimeBroker.exe","pid":21816,"consumption":0.0,"timestamp":1681744781.5132718,"container":null},{"exe":"","pid":4136,"consumption":0.0,"timestamp":1681744781.5132768,"container":null},{"exe":"","pid":10084,"consumption":0.0,"timestamp":1681744781.513282,"container":null},{"exe":"C:\\Windows\\System32\\SecurityHealthSystray.exe","pid":16284,"consumption":0.0,"timestamp":1681744781.5132873,"container":null},{"exe":"C:\\Windows\\ImmersiveControlPanel\\SystemSettings.exe","pid":6792,"consumption":0.0,"timestamp":1681744781.5132923,"container":null},{"exe":"","pid":5388,"consumption":0.0,"timestamp":1681744781.5132976,"container":null},{"exe":"C:\\Windows\\SystemApps\\Microsoft.Windows.StartMenuExperienceHost_cw5n1h2txyewy\\StartMenuExperienceHost.exe","pid":17452,"consumption":0.0,"timestamp":1681744781.5133026,"container":null},{"exe":"","pid":3196,"consumption":0.0,"timestamp":1681744781.5133078,"container":null},{"exe":"C:\\Windows\\System32\\dllhost.exe","pid":5972,"consumption":0.0,"timestamp":1681744781.5133135,"container":null},{"exe":"","pid":148,"consumption":0.0,"timestamp":1681744781.5133193,"container":null},{"exe":"C:\\Windows\\System32\\svchost.exe","pid":12088,"consumption":0.0,"timestamp":1681744781.5133247,"container":null},{"exe":"","pid":5520,"consumption":0.0,"timestamp":1681744781.5133305,"container":null},{"exe":"C:\\Windows\\System32\\RuntimeBroker.exe","pid":12540,"consumption":0.0,"timestamp":1681744781.513336,"container":null},{"exe":"","pid":2640,"consumption":0.0,"timestamp":1681744781.5133417,"container":null},{"exe":"","pid":6412,"consumption":0.0,"timestamp":1681744781.5133474,"container":null},{"exe":"","pid":3172,"consumption":0.0,"timestamp":1681744781.513353,"container":null},{"exe":"","pid":7864,"consumption":0.0,"timestamp":1681744781.5133588,"container":null},{"exe":"C:\\Windows\\SystemApps\\MicrosoftWindows.Client.CBS_cw5n1h2txyewy\\SearchHost.exe","pid":17620,"consumption":0.0,"timestamp":1681744781.5133648,"container":null},{"exe":"","pid":1428,"consumption":0.0,"timestamp":1681744781.5133705,"container":null},{"exe":"","pid":7812,"consumption":0.0,"timestamp":1681744781.5133765,"container":null}],"sockets":[]},{"host":{"consumption":7752258.0,"timestamp":1681744782.5393836},"consumers":[{"exe":"C:\\Program Files\\erl-23.3.4.11\\bin\\erl.exe","pid":9460,"consumption":619698.9,"timestamp":1681744782.5469687,"container":null},{"exe":"C:\\scaphandre\\target\\debug\\scaphandre.exe","pid":17220,"consumption":28168.133,"timestamp":1681744782.5469503,"container":null},{"exe":"C:\\Windows\\explorer.exe","pid":16684,"consumption":0.0,"timestamp":1681744782.5469234,"container":null},{"exe":"C:\\Windows\\System32\\backgroundTaskHost.exe","pid":19848,"consumption":0.0,"timestamp":1681744782.546927,"container":null},{"exe":"C:\\Windows\\System32\\ApplicationFrameHost.exe","pid":18076,"consumption":0.0,"timestamp":1681744782.5469282,"container":null},{"exe":"","pid":4772,"consumption":0.0,"timestamp":1681744782.5469294,"container":null},{"exe":"","pid":9140,"consumption":0.0,"timestamp":1681744782.5469306,"container":null},{"exe":"","pid":3564,"consumption":0.0,"timestamp":1681744782.5469317,"container":null},{"exe":"","pid":13904,"consumption":0.0,"timestamp":1681744782.546933,"container":null},{"exe":"","pid":1504,"consumption":0.0,"timestamp":1681744782.5469341,"container":null},{"exe":"C:\\Windows\\System32\\Intel\\DPTF\\dptf_helper.exe","pid":12468,"consumption":0.0,"timestamp":1681744782.5469353,"container":null},{"exe":"","pid":12356,"consumption":0.0,"timestamp":1681744782.5469368,"container":null},{"exe":"","pid":1820,"consumption":0.0,"timestamp":1681744782.5469382,"container":null},{"exe":"","pid":4508,"consumption":0.0,"timestamp":1681744782.5469394,"container":null},{"exe":"","pid":3432,"consumption":0.0,"timestamp":1681744782.5469408,"container":null},{"exe":"","pid":2152,"consumption":0.0,"timestamp":1681744782.5469422,"container":null},{"exe":"","pid":9224,"consumption":0.0,"timestamp":1681744782.546944,"container":null},{"exe":"","pid":776,"consumption":0.0,"timestamp":1681744782.5469456,"container":null},{"exe":"C:\\Program Files\\WindowsApps\\ReaderNotificationClient_1.0.4.0_x86__e1rzdqpraam7r\\AcrobatNotificationClient.exe","pid":15372,"consumption":0.0,"timestamp":1681744782.546947,"container":null},{"exe":"","pid":2976,"consumption":0.0,"timestamp":1681744782.5469487,"container":null},{"exe":"","pid":1896,"consumption":0.0,"timestamp":1681744782.5469522,"container":null},{"exe":"","pid":708,"consumption":0.0,"timestamp":1681744782.5469542,"container":null},{"exe":"","pid":3780,"consumption":0.0,"timestamp":1681744782.5469558,"container":null},{"exe":"C:\\Windows\\System32\\RuntimeBroker.exe","pid":3236,"consumption":0.0,"timestamp":1681744782.546958,"container":null},{"exe":"C:\\Program Files\\WindowsApps\\Microsoft.YourPhone_1.23022.140.0_x64__8wekyb3d8bbwe\\PhoneExperienceHost.exe","pid":17080,"consumption":0.0,"timestamp":1681744782.54696,"container":null},{"exe":"","pid":6816,"consumption":0.0,"timestamp":1681744782.5469625,"container":null},{"exe":"","pid":1760,"consumption":0.0,"timestamp":1681744782.5469644,"container":null},{"exe":"C:\\Windows\\SystemApps\\Microsoft.LockApp_cw5n1h2txyewy\\LockApp.exe","pid":2980,"consumption":0.0,"timestamp":1681744782.5469666,"container":null},{"exe":"","pid":3000,"consumption":0.0,"timestamp":1681744782.5469708,"container":null},{"exe":"","pid":15816,"consumption":0.0,"timestamp":1681744782.546973,"container":null},{"exe":"","pid":8516,"consumption":0.0,"timestamp":1681744782.5469751,"container":null},{"exe":"C:\\Windows\\System32\\svchost.exe","pid":15660,"consumption":0.0,"timestamp":1681744782.5469775,"container":null},{"exe":"","pid":1092,"consumption":0.0,"timestamp":1681744782.54698,"container":null},{"exe":"","pid":2436,"consumption":0.0,"timestamp":1681744782.5469823,"container":null},{"exe":"","pid":3536,"consumption":0.0,"timestamp":1681744782.546985,"container":null},{"exe":"C:\\Windows\\System32\\svchost.exe","pid":20928,"consumption":0.0,"timestamp":1681744782.5469875,"container":null},{"exe":"","pid":3720,"consumption":0.0,"timestamp":1681744782.5469904,"container":null},{"exe":"","pid":4564,"consumption":0.0,"timestamp":1681744782.546993,"container":null},{"exe":"","pid":11780,"consumption":0.0,"timestamp":1681744782.5469959,"container":null},{"exe":"C:\\Windows\\System32\\svchost.exe","pid":18060,"consumption":0.0,"timestamp":1681744782.5469987,"container":null},{"exe":"","pid":3336,"consumption":0.0,"timestamp":1681744782.5470018,"container":null},{"exe":"","pid":8756,"consumption":0.0,"timestamp":1681744782.547005,"container":null},{"exe":"","pid":108,"consumption":0.0,"timestamp":1681744782.547008,"container":null},{"exe":"","pid":4464,"consumption":0.0,"timestamp":1681744782.5470111,"container":null},{"exe":"C:\\Windows\\System32\\DriverStore\\FileRepository\\cui_dch.inf_amd64_7208949846a9b9dc\\igfxEM.exe","pid":10304,"consumption":0.0,"timestamp":1681744782.5470142,"container":null},{"exe":"","pid":2000,"consumption":0.0,"timestamp":1681744782.5470176,"container":null},{"exe":"","pid":2912,"consumption":0.0,"timestamp":1681744782.5470207,"container":null},{"exe":"C:\\Windows\\System32\\svchost.exe","pid":10180,"consumption":0.0,"timestamp":1681744782.5470238,"container":null},{"exe":"","pid":4588,"consumption":0.0,"timestamp":1681744782.547027,"container":null},{"exe":"","pid":11528,"consumption":0.0,"timestamp":1681744782.5470302,"container":null},{"exe":"","pid":3756,"consumption":0.0,"timestamp":1681744782.5470338,"container":null},{"exe":"","pid":4004,"consumption":0.0,"timestamp":1681744782.5470374,"container":null},{"exe":"C:\\Windows\\SystemApps\\MicrosoftWindows.Client.CBS_cw5n1h2txyewy\\TextInputHost.exe","pid":21300,"consumption":0.0,"timestamp":1681744782.547041,"container":null},{"exe":"","pid":11072,"consumption":0.0,"timestamp":1681744782.5470445,"container":null},{"exe":"","pid":1988,"consumption":0.0,"timestamp":1681744782.547048,"container":null},{"exe":"","pid":3276,"consumption":0.0,"timestamp":1681744782.547052,"container":null},{"exe":"","pid":9800,"consumption":0.0,"timestamp":1681744782.5470557,"container":null},{"exe":"","pid":17588,"consumption":0.0,"timestamp":1681744782.5470595,"container":null},{"exe":"","pid":11328,"consumption":0.0,"timestamp":1681744782.5470634,"container":null},{"exe":"C:\\Windows\\System32\\oobe\\UserOOBEBroker.exe","pid":5772,"consumption":0.0,"timestamp":1681744782.5470672,"container":null},{"exe":"","pid":1184,"consumption":0.0,"timestamp":1681744782.5470712,"container":null},{"exe":"C:\\Program Files\\WindowsApps\\MicrosoftWindows.Client.WebExperience_423.8900.0.0_x64__cw5n1h2txyewy\\Dashboard\\Widgets.exe","pid":13968,"consumption":0.0,"timestamp":1681744782.5470753,"container":null},{"exe":"","pid":952,"consumption":0.0,"timestamp":1681744782.547079,"container":null},{"exe":"","pid":1904,"consumption":0.0,"timestamp":1681744782.5470831,"container":null},{"exe":"","pid":4704,"consumption":0.0,"timestamp":1681744782.5470874,"container":null},{"exe":"","pid":5376,"consumption":0.0,"timestamp":1681744782.5470917,"container":null},{"exe":"C:\\Windows\\System32\\RuntimeBroker.exe","pid":11388,"consumption":0.0,"timestamp":1681744782.547096,"container":null},{"exe":"","pid":6176,"consumption":0.0,"timestamp":1681744782.5471003,"container":null},{"exe":"","pid":4448,"consumption":0.0,"timestamp":1681744782.5471046,"container":null},{"exe":"","pid":2608,"consumption":0.0,"timestamp":1681744782.547109,"container":null},{"exe":"","pid":4480,"consumption":0.0,"timestamp":1681744782.5471137,"container":null},{"exe":"","pid":3360,"consumption":0.0,"timestamp":1681744782.5471182,"container":null},{"exe":"C:\\Windows\\py.exe","pid":16520,"consumption":0.0,"timestamp":1681744782.547123,"container":null},{"exe":"","pid":4616,"consumption":0.0,"timestamp":1681744782.5471275,"container":null},{"exe":"","pid":2744,"consumption":0.0,"timestamp":1681744782.547132,"container":null},{"exe":"C:\\Program Files\\Realtek\\Audio\\HDA\\RAVBg64.exe","pid":4248,"consumption":0.0,"timestamp":1681744782.5471368,"container":null},{"exe":"","pid":1308,"consumption":0.0,"timestamp":1681744782.5471416,"container":null},{"exe":"C:\\Windows\\System32\\conhost.exe","pid":6264,"consumption":0.0,"timestamp":1681744782.547146,"container":null},{"exe":"","pid":3132,"consumption":0.0,"timestamp":1681744782.5471509,"container":null},{"exe":"C:\\Windows\\System32\\RuntimeBroker.exe","pid":13160,"consumption":0.0,"timestamp":1681744782.5471559,"container":null},{"exe":"C:\\Windows\\System32\\RuntimeBroker.exe","pid":21816,"consumption":0.0,"timestamp":1681744782.5471609,"container":null},{"exe":"","pid":4136,"consumption":0.0,"timestamp":1681744782.547172,"container":null},{"exe":"","pid":10084,"consumption":0.0,"timestamp":1681744782.5471776,"container":null},{"exe":"C:\\Windows\\System32\\SecurityHealthSystray.exe","pid":16284,"consumption":0.0,"timestamp":1681744782.5471828,"container":null},{"exe":"C:\\Windows\\ImmersiveControlPanel\\SystemSettings.exe","pid":6792,"consumption":0.0,"timestamp":1681744782.5471878,"container":null},{"exe":"","pid":5388,"consumption":0.0,"timestamp":1681744782.5471928,"container":null},{"exe":"C:\\Windows\\SystemApps\\Microsoft.Windows.StartMenuExperienceHost_cw5n1h2txyewy\\StartMenuExperienceHost.exe","pid":17452,"consumption":0.0,"timestamp":1681744782.547198,"container":null},{"exe":"","pid":3196,"consumption":0.0,"timestamp":1681744782.5472033,"container":null},{"exe":"C:\\Windows\\System32\\dllhost.exe","pid":5972,"consumption":0.0,"timestamp":1681744782.547209,"container":null},{"exe":"","pid":148,"consumption":0.0,"timestamp":1681744782.5472145,"container":null},{"exe":"C:\\Windows\\System32\\svchost.exe","pid":12088,"consumption":0.0,"timestamp":1681744782.5472205,"container":null},{"exe":"","pid":5520,"consumption":0.0,"timestamp":1681744782.547226,"container":null},{"exe":"C:\\Windows\\System32\\RuntimeBroker.exe","pid":12540,"consumption":0.0,"timestamp":1681744782.5472314,"container":null},{"exe":"","pid":2640,"consumption":0.0,"timestamp":1681744782.5472372,"container":null},{"exe":"","pid":6412,"consumption":0.0,"timestamp":1681744782.5472426,"container":null},{"exe":"","pid":3172,"consumption":0.0,"timestamp":1681744782.5472484,"container":null},{"exe":"","pid":7864,"consumption":0.0,"timestamp":1681744782.547254,"container":null},{"exe":"C:\\Windows\\SystemApps\\MicrosoftWindows.Client.CBS_cw5n1h2txyewy\\SearchHost.exe","pid":17620,"consumption":0.0,"timestamp":1681744782.5472598,"container":null},{"exe":"","pid":1428,"consumption":0.0,"timestamp":1681744782.5472658,"container":null},{"exe":"","pid":7812,"consumption":0.0,"timestamp":1681744782.5472717,"container":null}],"sockets":[]}]